fast_decision-0.2.6.dist-info/METADATA
fast_decision-0.2.6.dist-info/WHEEL
fast_decision-0.2.6.dist-info/licenses/LICENSE-APACHE
fast_decision-0.2.6.dist-info/licenses/LICENSE-MIT
fast_decision.pyi
fast_decision/__init__.py
fast_decision/__init__.pyi
fast_decision/fast_decision.cpython-313-x86_64-linux-gnu.so
fast_decision/py.typed
fast_decision-0.2.6.dist-info/RECORD
