Metadata-Version: 2.4
Name: fast-decision
Version: 0.2.6
Classifier: Programming Language :: Rust
Classifier: Programming Language :: Python :: Implementation :: CPython
Classifier: Programming Language :: Python :: Implementation :: PyPy
Classifier: Programming Language :: Python :: 3
Classifier: Programming Language :: Python :: 3.8
Classifier: Programming Language :: Python :: 3.9
Classifier: Programming Language :: Python :: 3.10
Classifier: Programming Language :: Python :: 3.11
Classifier: Programming Language :: Python :: 3.12
License-File: LICENSE-APACHE
License-File: LICENSE-MIT
Summary: High-performance rule engine
Keywords: rules-engine,decision-engine,rust,performance
Home-Page: https://github.com/almayce/fast-decision
Author-email: AK <kolchta@gmail.com>
License: MIT OR Apache-2.0
Requires-Python: >=3.8
Project-URL: Repository, https://github.com/almayce/fast-decision
Project-URL: Homepage, https://github.com/almayce/fast-decision
